{
    "data": [
        {
            "adult": false,
            "backdrop_path": "/o74zr3P3eYKKs7jUlWgkmADnpAg.jpg",
            "genre_ids": [
                10766
            ],
            "id": 231962,
            "origin_country": [
                "ZA"
            ],
            "original_language": "af",
            "original_name": "Diepe Waters",
            "overview": "A South African, Afrikaans-language telenovela which takes place in and around a competitive swimming club, Die Swartmarlyne.",
            "popularity": 456.586,
            "poster_path": "/9YpV8H6E0gxp946jPox0Oa53jp6.jpg",
            "first_air_date": "2022-10-03",
            "name": "Diepe Waters",
            "vote_average": 9.5,
            "vote_count": 2
        },
        {
            "adult": false,
            "backdrop_path": "/ypK5Qy3JnzFG72iJBNo36mQbdej.jpg",
            "genre_ids": [
                99
            ],
            "id": 62690,
            "origin_country": [
                "DE"
            ],
            "original_language": "de",
            "original_name": "Steel Buddies \u2013 Stahlharte Gesch\u00e4fte",
            "overview": "",
            "popularity": 450.377,
            "poster_path": "/w4EZDwvmTUYziaqMAywoJMmRnCr.jpg",
            "first_air_date": "2014-09-22",
            "name": "Steel Buddies \u2013 Stahlharte Gesch\u00e4fte",
            "vote_average": 9.0,
            "vote_count": 10
        },
        {
            "adult": false,
            "backdrop_path": "/xgyTnSUUDT4jYL3X6F3DKYeP9HE.jpg",
            "genre_ids": [
                35,
                18,
                10751
            ],
            "id": 119316,
            "origin_country": [
                "IN"
            ],
            "original_language": "hi",
            "original_name": "\u0935\u093e\u0917\u0932\u0947 \u0915\u0940 \u0926\u0941\u0928\u093f\u092f\u093e",
            "overview": "Three generations of the family live together, who share all their happiness and sorrows. Follow the story of this family as they bring laughter to each other's lives and will make your heart melt. A new generation of the old critically acclaimed show is here to take you on a roller coaster ride of emotions.",
            "popularity": 422.46,
            "poster_path": "/jKonm6Q3vw51Ytd4y7bJ70xJT7l.jpg",
            "first_air_date": "2021-02-08",
            "name": "Wagle Ki Duniya",
            "vote_average": 7.8,
            "vote_count": 13
        },
        {
            "adult": false,
            "backdrop_path": "/k3hODpzSAmFe86e5Y2DzQd286sL.jpg",
            "genre_ids": [
                10764
            ],
            "id": 75430,
            "origin_country": [
                "HU"
            ],
            "original_language": "hu",
            "original_name": "\u00c1zsia Expressz",
            "overview": "",
            "popularity": 412.579,
            "poster_path": "/xkjb2otTNmsZHjEJ55TFXgdrY0r.jpg",
            "first_air_date": "2017-11-07",
            "name": "\u00c1zsia Expressz",
            "vote_average": 7.3,
            "vote_count": 3
        },
        {
            "adult": false,
            "backdrop_path": "/5i7aAPgYXXVusuzE4IzYlCEmjcs.jpg",
            "genre_ids": [
                10764
            ],
            "id": 2612,
            "origin_country": [
                "US"
            ],
            "original_language": "en",
            "original_name": "Deadliest Catch",
            "overview": "Forty-foot waves, 700 pound crab pots, freezing temperatures and your mortality staring you in the face\u2026it's all in a day's work for these modern day prospectors. During each episode we will watch crews race to meet their quota and make it home safely.",
            "popularity": 406.07,
            "poster_path": "/thjh1mHkwGbTs3Wz4tiajuJbmbC.jpg",
            "first_air_date": "2005-04-12",
            "name": "Deadliest Catch",
            "vote_average": 7.1,
            "vote_count": 146
        },
        {
            "adult": false,
            "backdrop_path": "/vK3reGUkyx8kYgG3votZfIoOGWB.jpg",
            "genre_ids": [
                10764
            ],
            "id": 8106,
            "origin_country": [
                "GB"
            ],
            "original_language": "en",
            "original_name": "Homes Under the Hammer",
            "overview": "Homes Under the Hammer is a British renovation and auction series that originally screened on BBC One as part of the BBC's morning television schedule, the series has been running since 2003. Its main presenters are Lucy Alexander and Martin Roberts, although in series three Marc Woodward and Jasmine Birtles alternated presenting duties with Alexander and Roberts. The series is the BBC's most successful show in the 10:00am slot, regularly attaining a 30% market share for new episodes.",
            "popularity": 391.884,
            "poster_path": "/8oqAkf0SgVSn3rVgcZ34rAABztU.jpg",
            "first_air_date": "2003-11-17",
            "name": "Homes Under the Hammer",
            "vote_average": 4.2,
            "vote_count": 5
        },
        {
            "adult": false,
            "backdrop_path": "/qJnjJXBLgG4tummCm792nvNz7u1.jpg",
            "genre_ids": [
                10767
            ],
            "id": 23915,
            "origin_country": [
                "DE"
            ],
            "original_language": "de",
            "original_name": "Markus Lanz",
            "overview": "TV presenter Markus Lanz invites prominent guests and experts from all areas of public life to his colourful talk show. As a rule, there are four guests, introduced individually to contribute their personal experiences to the topics.",
            "popularity": 390.331,
            "poster_path": "/tr4cLn4ecRASV0SPM9FRv0AJOQF.jpg",
            "first_air_date": "2008-06-03",
            "name": "Markus Lanz",
            "vote_average": 5.2,
            "vote_count": 9
        },
        {
            "adult": false,
            "backdrop_path": "/8eez6fEywKCS1ow6seT3IQK7Ylc.jpg",
            "genre_ids": [
                10767,
                35
            ],
            "id": 1489,
            "origin_country": [
                "US"
            ],
            "original_language": "en",
            "original_name": "Jimmy Kimmel Live!",
            "overview": "Jimmy Kimmel Live! is an American late-night talk show, created and hosted by Jimmy Kimmel and broadcast on ABC.",
            "popularity": 378.892,
            "poster_path": "/z1CAt5BCQEmmqtkze8B1UelQzkY.jpg",
            "first_air_date": "2003-01-26",
            "name": "Jimmy Kimmel Live!",
            "vote_average": 5.6,
            "vote_count": 153
        },
        {
            "adult": false,
            "backdrop_path": "/aCiXh5QX6bg0BtpFEBXKaZYScB4.jpg",
            "genre_ids": [
                10763,
                10764,
                99
            ],
            "id": 203599,
            "origin_country": [
                "HK"
            ],
            "original_language": "cn",
            "original_name": "\u6771\u5f35\u897f\u671b",
            "overview": "Scoop is a comprehensive information programme of Television Broadcasts Limited.\n\nThe content of the program is mainly based on entertainment news and personal follow-up of the artists, and will also be interspersed with the latest trends of TVB dramas and artists. Some entertainment news content clips will be rebroadcast on the next day's \"Entertainment Live\".\n\nThis program will be broadcast on Jade Channel from 19:30-20:00 (Hong Kong time) from June 6, 2005, and will be broadcast every day from March 3, 2019, and will be broadcast on myTV (later myTV SUPER) to provide \"Program Review\".",
            "popularity": 377.69,
            "poster_path": "/qo6y0XvSBlKM3XCbYVdcR3a6qyQ.jpg",
            "first_air_date": "2005-06-06",
            "name": "Scoop",
            "vote_average": 7.2,
            "vote_count": 13
        },
        {
            "adult": false,
            "backdrop_path": "/aQK5OviWvzKF86OcyfYoixH5zLG.jpg",
            "genre_ids": [
                18,
                80
            ],
            "id": 226637,
            "origin_country": [
                "US"
            ],
            "original_language": "en",
            "original_name": "High Potential",
            "overview": "Morgan is a single mom with an exceptional mind, whose unconventional knack for solving crimes leads to an unusual and unstoppable partnership with a by-the-book seasoned detective.",
            "popularity": 362.041,
            "poster_path": "/sEWC7lzVKfuwXhzdahW4AX1F05s.jpg",
            "first_air_date": "2024-09-17",
            "name": "High Potential",
            "vote_average": 9.111,
            "vote_count": 18
        },
        {
            "adult": false,
            "backdrop_path": "/fZclJkehcPnU6vUGh5JXfpXidr3.jpg",
            "genre_ids": [
                10766,
                18
            ],
            "id": 2527,
            "origin_country": [
                "GB"
            ],
            "original_language": "en",
            "original_name": "Emmerdale",
            "overview": "The lives of several families in the Yorkshire Dales revolve around a farm and the nearby village. With murders, affairs, lies, deceit, laughter and tears, it's all there in the village.",
            "popularity": 355.926,
            "poster_path": "/ualtuRRNYa9Fj61wSuBVcuvaVDP.jpg",
            "first_air_date": "1972-10-16",
            "name": "Emmerdale",
            "vote_average": 4.033,
            "vote_count": 92
        },
        {
            "adult": false,
            "backdrop_path": "/eISJhQRXhzhAatbXipa78I1unjD.jpg",
            "genre_ids": [
                99
            ],
            "id": 262964,
            "origin_country": [
                "GB"
            ],
            "original_language": "en",
            "original_name": "SAS: Catching the Criminals",
            "overview": "Ex-SAS leader Billy Billingham takes viewers on an immersive journey that looks at how police and enforcement teams are increasingly using military and SAS tactics to catch criminals.",
            "popularity": 328.56,
            "poster_path": "/759ouoRAF7AQPvE8aXRIDgwdMdc.jpg",
            "first_air_date": "2024-09-09",
            "name": "SAS: Catching the Criminals",
            "vote_average": 0.0,
            "vote_count": 0
        },
        {
            "adult": false,
            "backdrop_path": "/4og4Eme2gHcTRaHVpZTSCDd7ZNY.jpg",
            "genre_ids": [
                10766,
                18,
                80
            ],
            "id": 1871,
            "origin_country": [
                "GB"
            ],
            "original_language": "en",
            "original_name": "EastEnders",
            "overview": "The everyday lives of working-class residents of Albert Square, a traditional Victorian square of terrace houses surrounding a park in the East End of London's Walford borough.",
            "popularity": 323.875,
            "poster_path": "/z4jgyI5TpoRZiJTNchkVkMrGQyz.jpg",
            "first_air_date": "1985-02-19",
            "name": "EastEnders",
            "vote_average": 4.1,
            "vote_count": 203
        },
        {
            "adult": false,
            "backdrop_path": "/1Jz9C5BOIjKPEWhm3zWcpDHJ0TT.jpg",
            "genre_ids": [
                10759,
                16,
                10765
            ],
            "id": 250598,
            "origin_country": [
                "JP"
            ],
            "original_language": "ja",
            "original_name": "\u65b0\u7c73\u30aa\u30c3\u30b5\u30f3\u5192\u967a\u8005\u3001\u6700\u5f37\u30d1\u30fc\u30c6\u30a3\u306b\u6b7b\u306c\u307b\u3069\u935b\u3048\u3089\u308c\u3066\u7121\u6575\u306b\u306a\u308b\u3002",
            "overview": "Normally, people choose to become adventurers in their teens. At 30 years old, Rick Gladiator bucks the trend by leaving his job as a guild clerk to become an adventurer. He begins as a novice F-rank with the fighting strength of an S-rank. After two years of brutal training with the continent\u2019s strongest party, Orichalcum Fist, Rick will defeat anyone who underestimates him!",
            "popularity": 319.708,
            "poster_path": "/2JZRQpLVwpmPTgdaKf3dFvhNy8z.jpg",
            "first_air_date": "2024-07-02",
            "name": "The Ossan Newbie Adventurer, Trained to Death by the Most Powerful Party, Became Invincible",
            "vote_average": 6.8,
            "vote_count": 5
        },
        {
            "adult": false,
            "backdrop_path": "/80n4VTYK6sTNFauaalDw4TL7ECK.jpg",
            "genre_ids": [
                10764
            ],
            "id": 234317,
            "origin_country": [
                "GB"
            ],
            "original_language": "en",
            "original_name": "My Mum, Your Dad",
            "overview": "A dating show with a difference for the whole family, My Mum, Your Dad follows a group of single parents who have been nominated by their grown-up kids for a second chance at love. Across 10 hour-long episodes, audiences will be able to follow the single parents, from all over the UK, and all walks of life, as they live together at a stunning country house retreat with one objective: to find true love.",
            "popularity": 317.26,
            "poster_path": "/jVX2qswGnxgsCtlGhcqxIfwXuMq.jpg",
            "first_air_date": "2023-09-11",
            "name": "My Mum, Your Dad",
            "vote_average": 0.0,
            "vote_count": 0
        },
        {
            "adult": false,
            "backdrop_path": "/oyZWiPvumwSYMrF2XbZH6yXQZ14.jpg",
            "genre_ids": [
                35,
                9648,
                80
            ],
            "id": 107113,
            "origin_country": [
                "US"
            ],
            "original_language": "en",
            "original_name": "Only Murders in the Building",
            "overview": "Three strangers share an obsession with true crime and suddenly find themselves wrapped up in one.",
            "popularity": 312.568,
            "poster_path": "/bZubW4eLAk2zqk44fSWRDTFfcba.jpg",
            "first_air_date": "2021-08-31",
            "name": "Only Murders in the Building",
            "vote_average": 8.326,
            "vote_count": 1387
        },
        {
            "adult": false,
            "backdrop_path": "/dDKJsVnuqARAcwtpKVlfheytHAa.jpg",
            "genre_ids": [
                10766,
                18
            ],
            "id": 1054,
            "origin_country": [
                "US"
            ],
            "original_language": "en",
            "original_name": "The Young and the Restless",
            "overview": "The rivalries, romances, hopes and fears of the residents of the fictional Midwestern metropolis, Genoa City. The lives and loves of a wide variety of characters mingle through the generations, dominated by the Newman, Abbott, Baldwin and Winters families.",
            "popularity": 310.543,
            "poster_path": "/4rdJWBQQV1Iqve8kYq8wdfcvUKo.jpg",
            "first_air_date": "1973-03-26",
            "name": "The Young and the Restless",
            "vote_average": 6.902,
            "vote_count": 143
        },
        {
            "adult": false,
            "backdrop_path": "/xr0Af75X7zHvEuDZUTfQvmR20ib.jpg",
            "genre_ids": [
                10767
            ],
            "id": 122430,
            "origin_country": [],
            "original_language": "es",
            "original_name": "Lo sabe, no lo sabe",
            "overview": "",
            "popularity": 306.467,
            "poster_path": "/v3XBjNXSFpe2I0EpLHSWdPDpvIG.jpg",
            "first_air_date": "2012-07-30",
            "name": "Lo sabe, no lo sabe",
            "vote_average": 0.0,
            "vote_count": 0
        },
        {
            "adult": false,
            "backdrop_path": "/zDIEftbezU42mNMLDGqnVxKSk9f.jpg",
            "genre_ids": [
                80,
                18
            ],
            "id": 253983,
            "origin_country": [
                "MX"
            ],
            "original_language": "es",
            "original_name": "Las azules",
            "overview": "In 1971, four women defy ultraconservative norms and join Mexico's first female police force\u2014only to discover that it's a publicity stunt to distract the media from a serial killer. As the body count grows, they make a pact to bring the killer to justice.",
            "popularity": 304.034,
            "poster_path": "/5JMYd2jYZGQ0KKcSQ8MH6k49XnF.jpg",
            "first_air_date": "2024-07-30",
            "name": "Women in Blue",
            "vote_average": 7.333,
            "vote_count": 15
        },
        {
            "adult": false,
            "backdrop_path": "/e7MSbwYRVqd4rZQQWcNuJvOSHLC.jpg",
            "genre_ids": [
                10766,
                18
            ],
            "id": 881,
            "origin_country": [
                "US"
            ],
            "original_language": "en",
            "original_name": "Days of Our Lives",
            "overview": "The Horton and Brady broods endure the romantic trials of life in Salem, a Midwestern hamlet filled with evil geniuses, star-crossed lovers and a rich family history.",
            "popularity": 298.372,
            "poster_path": "/ieyvdmqnlzWeVU7IF3rjqVVJax9.jpg",
            "first_air_date": "1965-11-08",
            "name": "Days of Our Lives",
            "vote_average": 5.939,
            "vote_count": 132
        }
    ],
    "type": "tvseries",
    "page": 5
}